TTS369.py
tts369-1.0.0.dist-info/WHEEL
tts369-1.0.0.dist-info/METADATA
tts369-1.0.0.dist-info/RECORD
