Metadata-Version: 2.1
Name: tts369
Version: 1.0.0
Summary: TTS("Your message").say()
Author: dudha369
Author-email: duduha2010@gmail.com
Requires-Python: >=3.6,<4.0
Classifier: Programming Language :: Python :: 3
Classifier: Programming Language :: Python :: 3.6
Classifier: Programming Language :: Python :: 3.7
Classifier: Programming Language :: Python :: 3.8
Classifier: Programming Language :: Python :: 3.9
